client/__init__.py
client/client.py
client/client_gui.py
client/client_resource.py
client/client_storage.py
my_messanger_client-0.0.0.dist-info/METADATA
my_messanger_client-0.0.0.dist-info/WHEEL
my_messanger_client-0.0.0.dist-info/top_level.txt
my_messanger_client-0.0.0.dist-info/RECORD
