Metadata-Version: 2.1
Name: my-messanger-client
Version: 0.0.0
Summary: messenger_client
Author: Andrey Matyukhin 
Author-email: matykhinand2021@gmail.com
Requires-Dist: PyQt5
Requires-Dist: sqlalchemy
Requires-Dist: pycryptodome
Requires-Dist: pycryptodomex
